{
    "vw": {
        "checks": [
            {
                "name": "sellLess",
                "label": "Дата продажи < 2 лет"
            },
            {
                "name": "sellAfter",
                "label": "Дата продажи > 15.01.2010"
            }
        ]
    },
    "vwcargo": {
        "checks": [
            {
                "name": "sellLess",
                "label": "Дата продажи < 2 лет"
            },
            {
                "name": "sellAfter",
                "label": "Дата продажи > 01.06.2010"
            },
            {
                "name": "modelInList",
                "label": "Модель входит в программу"
            }
        ]
    },
    "chevyko": {
        "checks": [
            {
                "name": "sellLess",
                "label": "Дата продажи < 1 года"
            },
            {
                "name": "sellAfter",
                "label": "Дата продажи > 15.12.2010"
            }
        ]
    },
    "chevyna": {
        "checks": [
            {
                "name": "sellLess",
                "label": "Дата продажи < 1 года"
            },
            {
                "name": "sellAfter",
                "label": "Дата продажи > 01.02.2010"
            },
            {
                "name": "modelInList",
                "label": "Модель входит в программу"
            }
        ]
    },
    "oldcad": {
        "checks": [
            {
                "name": "sellLess",
                "label": "Дата продажи < 1 года"
            },
            {
                "name": "sellAfter",
                "label": "Дата продажи > 01.02.2010"
            },
            {
                "name": "modelInList",
                "label": "Модель входит в программу"
            }
        ]
    },
    "opel": {
        "checks": [
            {
                "name": "sellLess",
                "label": "Дата продажи < 3 года"
            },
            {
                "name": "sellAfter",
                "label": "Дата продажи > 01.04.2011"
            },
            {
                "name": "modelInList",
                "label": "Модель входит в программу"
            }
        ]
    },
    "hum": {
        "checks": [
            {
                "name": "sellLess",
                "label": "Дата продажи < 1 года"
            },
            {
                "name": "sellAfter",
                "label": "Дата продажи > 01.02.2010"
            }
        ]
    },
    "cad2012": {
        "checks": [
            {
                "name": "sellLess",
                "label": "Дата продажи < 3 года"
            },
            {
                "name": "sellAfter",
                "label": "Дата продажи > 01.01.2012"
            },
            {
                "name": "modelInList",
                "label": "Модель входит в программу"
            }
        ]
    },
    "ford": {
        "checks": [
            {
                "name": "checkupLess",
                "label": "Дата последнего ТО < 1 года"
            },
            {
                "name": "sellAfter",
                "label": "Межсервисный интервал не пройден"
            }
        ]
    },
    "ruslan": {
        "checks": [
            {
                "name": "checkupLess",
                "label": "Дата последнего ТО < 1 года"
            }
        ]
    },
    "bp": {
        "checks": [
            {
                "label": "Обращение компании BP"
            }
        ]
    },
    "b2c": {
        "checks": [
            {
                "label": "Номер карты участника в списке карт"
            }
        ]
    },
    "b2cplat": {
        "checks": [
            {
                "label": "Номер карты участника в списке карт"
            }
        ]
    },
    "bentley": {
        "checks": [
            {
                "label": "Обращение компании ACTA"
            },
            {
                "label": "GOP предоставлена"
            }
        ]
    },
    "aston": {
        "checks": [
            {
                "label": "Обращение компании ACTA"
            },
            {
                "label": "GOP предоставлена"
            },
            {
                "label": "Клиент участвует в программе"
            }
        ]
    },
    "tele": {
        "checks": [
            {
                "label": "Контактное лицо из списка"
            }
        ]
    },
    "vtb24": {
        "checks": [
            {
                "label": "ФИО и год рождения в списке"
            }
        ]
    },
    "lyckoil": {
        "checks": [
            {
                "label": "Номер карты участника в списке"
            },
            {
                "label": "Программа действует"
            }
        ]
    },
    "unicredit": {
        "checks": [
            {
                "label": "Номер карты участника в списке"
            },
            {
                "label": "Программа действует"
            }
        ]
    },
    "rnbase": {
        "checks": [
            {
                "label": "Госномер в списке"
            },
            {
                "label": "Программа действует"
            }
        ]
    },
    "rnstandard": {
        "checks": [
            {
                "label": "Госномер в списке"
            },
            {
                "label": "Программа действует"
            }
        ]
    },
    "atlant": {
        "checks": [
            {
                "label": "VIN в списке участников программы"
            },
            {
                "label": "Программа действует"
            },
            {
                "label": "Пробег не исчерпан"
            }
        ]
    },
    "chartis": {
        "checks": [
            {
                "label": "VIN в списке участников программы"
            },
            {
                "label": "Программа действует"
            },
            {
                "label": "Пробег не исчерпан"
            }
        ]
    }
}